summariser/__init__.py
summariser/core.py
summariser-0.1.0.dist-info/licenses/LICENSE
summariser-0.1.0.dist-info/METADATA
summariser-0.1.0.dist-info/WHEEL
summariser-0.1.0.dist-info/top_level.txt
summariser-0.1.0.dist-info/RECORD
